[
  {
    "id": 1,
    "name": "Push-ups",
    "type": "strength",
    "muscle_group": "chest",
    "equipment_needed": [],
    "duration_per_rep_seconds": 3,
    "reps_per_set": 12,
    "sets": 3,
    "rest_between_sets_seconds": 60,
    "description": "Standard push-ups targeting chest, shoulders, and triceps"
  },
  {
    "id": 2,
    "name": "Squats",
    "type": "strength",
    "muscle_group": "legs",
    "equipment_needed": [],
    "duration_per_rep_seconds": 3,
    "reps_per_set": 15,
    "sets": 3,
    "rest_between_sets_seconds": 60,
    "description": "Bodyweight squats for leg and glute strength"
  },
  {
    "id": 3,
    "name": "Lunges",
    "type": "strength",
    "muscle_group": "legs",
    "equipment_needed": [],
    "duration_per_rep_seconds": 4,
    "reps_per_set": 10,
    "sets": 3,
    "rest_between_sets_seconds": 60,
    "description": "Alternating lunges for leg strength and balance"
  },
  {
    "id": 4,
    "name": "Plank",
    "type": "strength",
    "muscle_group": "core",
    "equipment_needed": [],
    "duration_per_rep_seconds": 30,
    "reps_per_set": 1,
    "sets": 3,
    "rest_between_sets_seconds": 60,
    "description": "Hold plank position for core strength"
  },
  {
    "id": 5,
    "name": "Jumping Jacks",
    "type": "cardio",
    "muscle_group": "full_body",
    "equipment_needed": [],
    "duration_per_rep_seconds": 1,
    "reps_per_set": 30,
    "sets": 3,
    "rest_between_sets_seconds": 45,
    "description": "Classic cardio exercise for full-body warm-up"
  },
  {
    "id": 6,
    "name": "Mountain Climbers",
    "type": "cardio",
    "muscle_group": "core",
    "equipment_needed": [],
    "duration_per_rep_seconds": 1,
    "reps_per_set": 20,
    "sets": 3,
    "rest_between_sets_seconds": 60,
    "description": "High-intensity core and cardio exercise"
  },
  {
    "id": 7,
    "name": "Burpees",
    "type": "cardio",
    "muscle_group": "full_body",
    "equipment_needed": [],
    "duration_per_rep_seconds": 5,
    "reps_per_set": 8,
    "sets": 3,
    "rest_between_sets_seconds": 90,
    "description": "Full-body high-intensity exercise"
  },
  {
    "id": 8,
    "name": "Dumbbell Bicep Curls",
    "type": "strength",
    "muscle_group": "arms",
    "equipment_needed": ["dumbbell"],
    "duration_per_rep_seconds": 3,
    "reps_per_set": 12,
    "sets": 3,
    "rest_between_sets_seconds": 60,
    "description": "Bicep curls using dumbbells"
  },
  {
    "id": 9,
    "name": "Dumbbell Shoulder Press",
    "type": "strength",
    "muscle_group": "shoulders",
    "equipment_needed": ["dumbbell"],
    "duration_per_rep_seconds": 3,
    "reps_per_set": 10,
    "sets": 3,
    "rest_between_sets_seconds": 60,
    "description": "Overhead shoulder press with dumbbells"
  },
  {
    "id": 10,
    "name": "Dumbbell Rows",
    "type": "strength",
    "muscle_group": "back",
    "equipment_needed": ["dumbbell"],
    "duration_per_rep_seconds": 3,
    "reps_per_set": 12,
    "sets": 3,
    "rest_between_sets_seconds": 60,
    "description": "Bent-over rows targeting back muscles"
  },
  {
    "id": 11,
    "name": "Dumbbell Chest Press",
    "type": "strength",
    "muscle_group": "chest",
    "equipment_needed": ["dumbbell", "bench"],
    "duration_per_rep_seconds": 3,
    "reps_per_set": 10,
    "sets": 3,
    "rest_between_sets_seconds": 60,
    "description": "Chest press using dumbbells and bench"
  },
  {
    "id": 12,
    "name": "Pull-ups",
    "type": "strength",
    "muscle_group": "back",
    "equipment_needed": ["pull_up_bar"],
    "duration_per_rep_seconds": 4,
    "reps_per_set": 8,
    "sets": 3,
    "rest_between_sets_seconds": 90,
    "description": "Pull-ups for back and arm strength"
  },
  {
    "id": 13,
    "name": "Chin-ups",
    "type": "strength",
    "muscle_group": "arms",
    "equipment_needed": ["pull_up_bar"],
    "duration_per_rep_seconds": 4,
    "reps_per_set": 8,
    "sets": 3,
    "rest_between_sets_seconds": 90,
    "description": "Chin-ups targeting biceps and back"
  },
  {
    "id": 14,
    "name": "Kettlebell Swings",
    "type": "strength",
    "muscle_group": "full_body",
    "equipment_needed": ["kettlebell"],
    "duration_per_rep_seconds": 2,
    "reps_per_set": 15,
    "sets": 3,
    "rest_between_sets_seconds": 60,
    "description": "Dynamic kettlebell swings for full-body strength"
  },
  {
    "id": 15,
    "name": "Kettlebell Goblet Squats",
    "type": "strength",
    "muscle_group": "legs",
    "equipment_needed": ["kettlebell"],
    "duration_per_rep_seconds": 3,
    "reps_per_set": 12,
    "sets": 3,
    "rest_between_sets_seconds": 60,
    "description": "Squats holding kettlebell for added resistance"
  },
  {
    "id": 16,
    "name": "Resistance Band Rows",
    "type": "strength",
    "muscle_group": "back",
    "equipment_needed": ["resistance_band"],
    "duration_per_rep_seconds": 3,
    "reps_per_set": 15,
    "sets": 3,
    "rest_between_sets_seconds": 60,
    "description": "Rowing motion using resistance bands"
  },
  {
    "id": 17,
    "name": "Resistance Band Chest Press",
    "type": "strength",
    "muscle_group": "chest",
    "equipment_needed": ["resistance_band"],
    "duration_per_rep_seconds": 3,
    "reps_per_set": 15,
    "sets": 3,
    "rest_between_sets_seconds": 60,
    "description": "Chest press using resistance bands"
  },
  {
    "id": 18,
    "name": "Bench Press",
    "type": "strength",
    "muscle_group": "chest",
    "equipment_needed": ["barbell", "bench"],
    "duration_per_rep_seconds": 3,
    "reps_per_set": 8,
    "sets": 3,
    "rest_between_sets_seconds": 90,
    "description": "Classic bench press with barbell"
  },
  {
    "id": 19,
    "name": "Deadlifts",
    "type": "strength",
    "muscle_group": "full_body",
    "equipment_needed": ["barbell"],
    "duration_per_rep_seconds": 4,
    "reps_per_set": 6,
    "sets": 3,
    "rest_between_sets_seconds": 120,
    "description": "Deadlifts for full-body strength"
  },
  {
    "id": 20,
    "name": "Tricep Dips",
    "type": "strength",
    "muscle_group": "arms",
    "equipment_needed": ["bench"],
    "duration_per_rep_seconds": 3,
    "reps_per_set": 12,
    "sets": 3,
    "rest_between_sets_seconds": 60,
    "description": "Tricep dips using bench"
  },
  {
    "id": 21,
    "name": "Calf Raises",
    "type": "strength",
    "muscle_group": "legs",
    "equipment_needed": [],
    "duration_per_rep_seconds": 2,
    "reps_per_set": 20,
    "sets": 3,
    "rest_between_sets_seconds": 45,
    "description": "Standing calf raises"
  },
  {
    "id": 22,
    "name": "Side Plank",
    "type": "strength",
    "muscle_group": "core",
    "equipment_needed": [],
    "duration_per_rep_seconds": 20,
    "reps_per_set": 1,
    "sets": 2,
    "rest_between_sets_seconds": 60,
    "description": "Side plank for core stability (each side)"
  },
  {
    "id": 23,
    "name": "Russian Twists",
    "type": "strength",
    "muscle_group": "core",
    "equipment_needed": [],
    "duration_per_rep_seconds": 2,
    "reps_per_set": 20,
    "sets": 3,
    "rest_between_sets_seconds": 60,
    "description": "Core rotation exercise"
  },
  {
    "id": 24,
    "name": "Wall Sits",
    "type": "strength",
    "muscle_group": "legs",
    "equipment_needed": [],
    "duration_per_rep_seconds": 30,
    "reps_per_set": 1,
    "sets": 3,
    "rest_between_sets_seconds": 60,
    "description": "Isometric leg exercise against wall"
  },
  {
    "id": 25,
    "name": "High Knees",
    "type": "cardio",
    "muscle_group": "legs",
    "equipment_needed": [],
    "duration_per_rep_seconds": 1,
    "reps_per_set": 30,
    "sets": 3,
    "rest_between_sets_seconds": 45,
    "description": "Running in place with high knees"
  },
  {
    "id": 26,
    "name": "Stretching Routine",
    "type": "flexibility",
    "muscle_group": "full_body",
    "equipment_needed": [],
    "duration_per_rep_seconds": 30,
    "reps_per_set": 8,
    "sets": 1,
    "rest_between_sets_seconds": 10,
    "description": "Full-body stretching routine"
  }
]
